{
"meta":{"test_sets":[],"test_metrics":[],"learn_metrics":[{"best_value":"Min","name":"RMSE"}],"launch_mode":"Train","parameters":"","iteration_count":100,"learn_sets":["learn"],"name":"experiment"},
"iterations":[
{"learn":[14.005006],"iteration":0,"passed_time":0.001329017215,"remaining_time":0.1315727043},
{"learn":[13.14441192],"iteration":1,"passed_time":0.002322499666,"remaining_time":0.1138024836},
{"learn":[12.34258257],"iteration":2,"passed_time":0.003463682243,"remaining_time":0.1119923925},
{"learn":[11.64527793],"iteration":3,"passed_time":0.004266806861,"remaining_time":0.1024033647},
{"learn":[11.02766183],"iteration":4,"passed_time":0.00533939469,"remaining_time":0.1014484991},
{"learn":[10.43485794],"iteration":5,"passed_time":0.006414615501,"remaining_time":0.1004956429},
{"learn":[9.890641275],"iteration":6,"passed_time":0.007397828662,"remaining_time":0.09828543793},
{"learn":[9.492161212],"iteration":7,"passed_time":0.008407358386,"remaining_time":0.09668462144},
{"learn":[9.105082953],"iteration":8,"passed_time":0.009480264217,"remaining_time":0.09585600486},
{"learn":[8.674157135],"iteration":9,"passed_time":0.01052391954,"remaining_time":0.09471527584},
{"learn":[8.341743544],"iteration":10,"passed_time":0.01154006011,"remaining_time":0.09336957724},
{"learn":[8.049372916],"iteration":11,"passed_time":0.01257382992,"remaining_time":0.09220808606},
{"learn":[7.757318612],"iteration":12,"passed_time":0.01344190551,"remaining_time":0.08995736765},
{"learn":[7.522206899],"iteration":13,"passed_time":0.01438650035,"remaining_time":0.08837421643},
{"learn":[7.297756655],"iteration":14,"passed_time":0.01555512007,"remaining_time":0.08814568039},
{"learn":[7.088359431],"iteration":15,"passed_time":0.01647403151,"remaining_time":0.08648866542},
{"learn":[6.882113791],"iteration":16,"passed_time":0.01755736421,"remaining_time":0.0857212488},
{"learn":[6.704728832],"iteration":17,"passed_time":0.01850190794,"remaining_time":0.08428646952},
{"learn":[6.563881962],"iteration":18,"passed_time":0.01944286847,"remaining_time":0.08288801822},
{"learn":[6.418790279],"iteration":19,"passed_time":0.0205230609,"remaining_time":0.08209224362},
{"learn":[6.315756953],"iteration":20,"passed_time":0.02151826161,"remaining_time":0.08094965081},
{"learn":[6.210157751],"iteration":21,"passed_time":0.02256340946,"remaining_time":0.07999754261},
{"learn":[6.115058449],"iteration":22,"passed_time":0.02350911446,"remaining_time":0.07870442668},
{"learn":[6.014819884],"iteration":23,"passed_time":0.02444210223,"remaining_time":0.07739999038},
{"learn":[5.93117229],"iteration":24,"passed_time":0.02535937917,"remaining_time":0.07607813752},
{"learn":[5.844857622],"iteration":25,"passed_time":0.02648596016,"remaining_time":0.07538311737},
{"learn":[5.771145213],"iteration":26,"passed_time":0.02739727551,"remaining_time":0.07407411527},
{"learn":[5.704018229],"iteration":27,"passed_time":0.02841365269,"remaining_time":0.07306367835},
{"learn":[5.665806474],"iteration":28,"passed_time":0.02941777354,"remaining_time":0.07202282487},
{"learn":[5.616500369],"iteration":29,"passed_time":0.03039051819,"remaining_time":0.0709112091},
{"learn":[5.558023666],"iteration":30,"passed_time":0.03138551446,"remaining_time":0.06985808057},
{"learn":[5.510080976],"iteration":31,"passed_time":0.03231704471,"remaining_time":0.06867372001},
{"learn":[5.468747792],"iteration":32,"passed_time":0.03328038842,"remaining_time":0.06756927346},
{"learn":[5.429275534],"iteration":33,"passed_time":0.03421348219,"remaining_time":0.0664144066},
{"learn":[5.402117324],"iteration":34,"passed_time":0.03539754914,"remaining_time":0.06573830555},
{"learn":[5.367635151],"iteration":35,"passed_time":0.03641048414,"remaining_time":0.06472974958},
{"learn":[5.345181232],"iteration":36,"passed_time":0.03741958513,"remaining_time":0.06371442873},
{"learn":[5.319151269],"iteration":37,"passed_time":0.03836339253,"remaining_time":0.0625929036},
{"learn":[5.296134146],"iteration":38,"passed_time":0.03931516702,"remaining_time":0.06149295355},
{"learn":[5.269629003],"iteration":39,"passed_time":0.0402033941,"remaining_time":0.06030509116},
{"learn":[5.251147059],"iteration":40,"passed_time":0.0411193962,"remaining_time":0.05917181405},
{"learn":[5.248003302],"iteration":41,"passed_time":0.04150951375,"remaining_time":0.05732266185},
{"learn":[5.232376509],"iteration":42,"passed_time":0.04236520714,"remaining_time":0.05615853039},
{"learn":[5.213524255],"iteration":43,"passed_time":0.04344599914,"remaining_time":0.05529490799},
{"learn":[5.189691584],"iteration":44,"passed_time":0.04461110001,"remaining_time":0.05452467779},
{"learn":[5.166052198],"iteration":45,"passed_time":0.04564380603,"remaining_time":0.05358185925},
{"learn":[5.140406659],"iteration":46,"passed_time":0.04669964528,"remaining_time":0.05266130212},
{"learn":[5.118929684],"iteration":47,"passed_time":0.04783683579,"remaining_time":0.05182323878},
{"learn":[5.108792602],"iteration":48,"passed_time":0.04883797159,"remaining_time":0.05083135818},
{"learn":[5.098141225],"iteration":49,"passed_time":0.04976803865,"remaining_time":0.04976803865},
{"learn":[5.085926393],"iteration":50,"passed_time":0.05073792034,"remaining_time":0.04874819797},
{"learn":[5.067816804],"iteration":51,"passed_time":0.05171559212,"remaining_time":0.04773746965},
{"learn":[5.049834901],"iteration":52,"passed_time":0.05271758728,"remaining_time":0.04674955853},
{"learn":[5.03838627],"iteration":53,"passed_time":0.05367525522,"remaining_time":0.04572336556},
{"learn":[5.033534248],"iteration":54,"passed_time":0.05439373734,"remaining_time":0.04450396692},
{"learn":[5.023726885],"iteration":55,"passed_time":0.05532281254,"remaining_time":0.04346792414},
{"learn":[5.01290392],"iteration":56,"passed_time":0.05630571338,"remaining_time":0.04247623992},
{"learn":[5.005569127],"iteration":57,"passed_time":0.05742549754,"remaining_time":0.04158398098},
{"learn":[4.989969032],"iteration":58,"passed_time":0.05842810315,"remaining_time":0.04060258016},
{"learn":[4.976762446],"iteration":59,"passed_time":0.05946738405,"remaining_time":0.0396449227},
{"learn":[4.967222715],"iteration":60,"passed_time":0.06040456831,"remaining_time":0.03861931416},
{"learn":[4.954407599],"iteration":61,"passed_time":0.06137091695,"remaining_time":0.03761443297},
{"learn":[4.942125056],"iteration":62,"passed_time":0.06235016076,"remaining_time":0.03661834838},
{"learn":[4.930230716],"iteration":63,"passed_time":0.06327218502,"remaining_time":0.03559060408},
{"learn":[4.921695642],"iteration":64,"passed_time":0.06429386129,"remaining_time":0.03461977146},
{"learn":[4.906405625],"iteration":65,"passed_time":0.06534384163,"remaining_time":0.03366197902},
{"learn":[4.894330248],"iteration":66,"passed_time":0.06642597189,"remaining_time":0.03271726974},
{"learn":[4.88211557],"iteration":67,"passed_time":0.06748447961,"remaining_time":0.03175740217},
{"learn":[4.877946398],"iteration":68,"passed_time":0.06847893736,"remaining_time":0.0307658994},
{"learn":[4.863182126],"iteration":69,"passed_time":0.06948426208,"remaining_time":0.02977896946},
{"learn":[4.84646533],"iteration":70,"passed_time":0.07043052737,"remaining_time":0.0287673985},
{"learn":[4.838014752],"iteration":71,"passed_time":0.0715238743,"remaining_time":0.02781484001},
{"learn":[4.82981137],"iteration":72,"passed_time":0.07261314399,"remaining_time":0.02685691627},
{"learn":[4.817094767],"iteration":73,"passed_time":0.07361330212,"remaining_time":0.02586413318},
{"learn":[4.808314151],"iteration":74,"passed_time":0.07458354912,"remaining_time":0.02486118304},
{"learn":[4.796235023],"iteration":75,"passed_time":0.07559053956,"remaining_time":0.0238706967},
{"learn":[4.784434534],"iteration":76,"passed_time":0.07656772488,"remaining_time":0.02287087886},
{"learn":[4.774402487],"iteration":77,"passed_time":0.07748958162,"remaining_time":0.02185603584},
{"learn":[4.76731896],"iteration":78,"passed_time":0.0784521502,"remaining_time":0.02085436904},
{"learn":[4.75934113],"iteration":79,"passed_time":0.07937882998,"remaining_time":0.0198447075},
{"learn":[4.754106378],"iteration":80,"passed_time":0.08032166161,"remaining_time":0.01884088359},
{"learn":[4.744002932],"iteration":81,"passed_time":0.08122242611,"remaining_time":0.01782931305},
{"learn":[4.731700554],"iteration":82,"passed_time":0.08221246875,"remaining_time":0.01683869842},
{"learn":[4.723284153],"iteration":83,"passed_time":0.08329439031,"remaining_time":0.01586559816},
{"learn":[4.712232782],"iteration":84,"passed_time":0.08431482865,"remaining_time":0.01487908741},
{"learn":[4.703046867],"iteration":85,"passed_time":0.08542145784,"remaining_time":0.01390581872},
{"learn":[4.698601855],"iteration":86,"passed_time":0.08634163182,"remaining_time":0.01290162315},
{"learn":[4.692429407],"iteration":87,"passed_time":0.08744410427,"remaining_time":0.01192419604},
{"learn":[4.675027364],"iteration":88,"passed_time":0.0885998203,"remaining_time":0.01095053959},
{"learn":[4.662368584],"iteration":89,"passed_time":0.0897922722,"remaining_time":0.009976919133},
{"learn":[4.646206172],"iteration":90,"passed_time":0.09080892763,"remaining_time":0.008981102732},
{"learn":[4.641245848],"iteration":91,"passed_time":0.09177975858,"remaining_time":0.007980848572},
{"learn":[4.633900435],"iteration":92,"passed_time":0.09275500844,"remaining_time":0.006981559775},
{"learn":[4.624738236],"iteration":93,"passed_time":0.09382450805,"remaining_time":0.005988798386},
{"learn":[4.612798287],"iteration":94,"passed_time":0.09481699533,"remaining_time":0.004990368175},
{"learn":[4.605222001],"iteration":95,"passed_time":0.09578731521,"remaining_time":0.003991138134},
{"learn":[4.601725912],"iteration":96,"passed_time":0.09674162331,"remaining_time":0.002992008968},
{"learn":[4.59722371],"iteration":97,"passed_time":0.0976872914,"remaining_time":0.001993618192},
{"learn":[4.580235665],"iteration":98,"passed_time":0.09879334516,"remaining_time":0.0009979125774},
{"learn":[4.57591791],"iteration":99,"passed_time":0.09973227275,"remaining_time":0}
]}